amazon_buddy/__init__.py
amazon_buddy/_parser.py
amazon_buddy/_rh.py
amazon_buddy/amazon_buddy.py
amazon_buddy/_filter/__init__.py
amazon_buddy/_filter/product_filter.py
amazon_buddy/_filter/review_filter.py
amazon_buddy/models/__init__.py
amazon_buddy/models/base_product.py
amazon_buddy/models/product.py
amazon_buddy/models/product_detail.py
amazon_buddy/models/product_image_set.py
amazon_buddy/models/product_video.py
amazon_buddy/models/review.py
amazon_buddy/models/review_image.py
amazon_buddy/models/search_result_product.py
amazon_buddy/models/enums/__init__.py
amazon_buddy/models/enums/amazon_error.py
amazon_buddy/models/enums/category.py
amazon_buddy/models/enums/product_condition.py
amazon_buddy/models/enums/review_rating_filter.py
amazon_buddy/models/enums/review_sort_type.py
amazon_buddy/models/enums/sort_type.py
amazon_buddy-2.0.29.dist-info/METADATA
amazon_buddy-2.0.29.dist-info/WHEEL
amazon_buddy-2.0.29.dist-info/top_level.txt
amazon_buddy-2.0.29.dist-info/RECORD
