Metadata-Version: 2.1
Name: amazon-buddy
Version: 2.0.29
Summary: python wrapper for the amazon_buddy npm package
Home-page: https://github.com/kkristof200/py_amazon_buddy
Author: Kristof
License: UNKNOWN
Platform: UNKNOWN
Classifier: Programming Language :: Python :: 3
Classifier: License :: OSI Approved :: MIT License
Classifier: Operating System :: OS Independent
Requires-Python: >=3.5
Requires-Dist: beautifulsoup4 (>=4.10.0)
Requires-Dist: jsoncodable (>=0.1.7)
Requires-Dist: kcu (>=0.0.72)
Requires-Dist: ksimpleapi (>=0.0.41)
Requires-Dist: noraise (>=0.0.16)
Requires-Dist: requests (>=2.26.0)
Requires-Dist: Unidecode (>=1.3.2)
